README.rst
setup.py
Flask_Json_Syslog.egg-info/PKG-INFO
Flask_Json_Syslog.egg-info/SOURCES.txt
Flask_Json_Syslog.egg-info/dependency_links.txt
Flask_Json_Syslog.egg-info/not-zip-safe
Flask_Json_Syslog.egg-info/requires.txt
Flask_Json_Syslog.egg-info/top_level.txt
flask_json_syslog/__init__.py
flask_json_syslog/flask_json_syslog.py