Metadata-Version: 1.1
Name: Flask-Json-Syslog
Version: 0.1.25
Summary: Output syslog of the json format.
Home-page: https://github.com/nabetama/Flask-Json-Syslog
Author: Mao Nabeta
Author-email: mao.nabeta@gmail.com
License: MIT
Keywords: Flask,syslog,json
Platform: any
Classifier: Environment :: Web Environment
Classifier: Intended Audience :: Developers
Classifier: License :: OSI Approved :: MIT License
Classifier: Operating System :: OS Independent
Classifier: Programming Language :: Python
Classifier: Topic :: Internet :: WWW/HTTP :: Dynamic Content
Classifier: Topic :: Software Development :: Libraries :: Python Modules
Provides: Flask
Provides: syslog
Provides: json
